[
  {
    "timestamp": 1766129901054,
    "user": "poemstars🌼🌟",
    "userId": "spotify:user:21jq6cmbitks7givwb7zvsyxy",
    "track": "Gugatan Rakyat Semesta",
    "artist": ".Feast",
    "uri": "spotify:track:3Li1q9Z1AyDQbpadhERTPU",
    "imageUrl": "https://i.scdn.co/image/ab67616d0000b273471f8a4822a3ca180612d006"
  },
  {
    "timestamp": 1766129630632,
    "user": "poemstars🌼🌟",
    "userId": "spotify:user:21jq6cmbitks7givwb7zvsyxy",
    "track": "Sectumsempra",
    "artist": ".Feast",
    "uri": "spotify:track:7mrdjnIZLtWWszL90shouf",
    "imageUrl": "https://i.scdn.co/image/ab67616d0000b273a139f95c8185d8f334424732"
  },
  {
    "timestamp": 1766129362385,
    "user": "poemstars🌼🌟",
    "userId": "spotify:user:21jq6cmbitks7givwb7zvsyxy",
    "track": "Money In The Grave (Drake ft. Rick Ross)",
    "artist": "Drake, Rick Ross",
    "uri": "spotify:track:5ry2OE6R2zPQFDO85XkgRb",
    "imageUrl": "https://i.scdn.co/image/ab67616d0000b2733f3b653b0a7b9e889a712c3d"
  },
  {
    "timestamp": 1766122097253,
    "user": "poemstars🌼🌟",
    "userId": "spotify:user:21jq6cmbitks7givwb7zvsyxy",
    "track": "Kesempatan Kedua",
    "artist": "Tangga",
    "uri": "spotify:track:6W9EPH4b6fkgkERorDnuRz",
    "imageUrl": "https://i.scdn.co/image/ab67616d0000b2731aac1c15810ad41ab344b615"
  },
  {
    "timestamp": 1766065784150,
    "user": "poemstars🌼🌟",
    "userId": "spotify:user:21jq6cmbitks7givwb7zvsyxy",
    "track": "Cinta Tak Mungkin Berhenti",
    "artist": "Tangga",
    "uri": "spotify:track:4xthpyTiqIwZMJzX6UmLtK",
    "imageUrl": "https://i.scdn.co/image/ab67616d0000b273b0ce52706ab700bfaae3466b"
  },
  {
    "timestamp": 1766065517414,
    "user": "poemstars🌼🌟",
    "userId": "spotify:user:21jq6cmbitks7givwb7zvsyxy",
    "track": "Cinta Begini",
    "artist": "Tangga",
    "uri": "spotify:track:4387TltnnL2gMSYdr4UPhG",
    "imageUrl": "https://i.scdn.co/image/ab67616d0000b2730dc75502ea62a2a25fc06a4d"
  },
  {
    "timestamp": 1766065277233,
    "user": "poemstars🌼🌟",
    "userId": "spotify:user:21jq6cmbitks7givwb7zvsyxy",
    "track": "Biarkanlah",
    "artist": "Raisa",
    "uri": "spotify:track:0FERqRAVmXwPasxY5Jt8k1",
    "imageUrl": "https://i.scdn.co/image/ab67616d0000b273f018e2376d8060e0ba1112ab"
  },
  {
    "timestamp": 1766065004001,
    "user": "poemstars🌼🌟",
    "userId": "spotify:user:21jq6cmbitks7givwb7zvsyxy",
    "track": "Terjebak Nostalgia",
    "artist": "Raisa",
    "uri": "spotify:track:5i29InIyuEG5121x1onevN",
    "imageUrl": "https://i.scdn.co/image/ab67616d0000b2738bd2fdd47fa594b1362682a9"
  },
  {
    "timestamp": 1766064733802,
    "user": "poemstars🌼🌟",
    "userId": "spotify:user:21jq6cmbitks7givwb7zvsyxy",
    "track": "LDR",
    "artist": "Raisa",
    "uri": "spotify:track:6WIgm0evaMly8GH6VzdAo8",
    "imageUrl": "https://i.scdn.co/image/ab67616d0000b273ebbeac340a9e77f9f652eb15"
  },
  {
    "timestamp": 1766064226975,
    "user": "poemstars🌼🌟",
    "userId": "spotify:user:21jq6cmbitks7givwb7zvsyxy",
    "track": "Mantan Terindah",
    "artist": "Yovie Widianto, Raisa",
    "uri": "spotify:track:1wE4Iqv0tXXuZBA67PoGvw",
    "imageUrl": "https://i.scdn.co/image/ab67616d0000b27395f411458f0d6ee98424bf6c"
  }
]