[
  {
    "timestamp": 1767338821314,
    "user": "poemstars🌼🌟",
    "userId": "spotify:user:21jq6cmbitks7givwb7zvsyxy",
    "track": "Cinta 'Kan Membawamu Kembali",
    "artist": "Dewa 19",
    "uri": "spotify:track:6MwIBSBiAMGomp4I80Xkgw",
    "imageUrl": "https://i.scdn.co/image/f59c02125f70dbce2385090ddde01625c7cfb5c1"
  },
  {
    "timestamp": 1767338521284,
    "user": "poemstars🌼🌟",
    "userId": "spotify:user:21jq6cmbitks7givwb7zvsyxy",
    "track": "Slow Dancing in a Burning Room",
    "artist": "John Mayer",
    "uri": "spotify:track:75zIfJpcYFYHSBMVlmdiYc",
    "imageUrl": "https://i.scdn.co/image/ab67616d0000b273fa8e8cc9d6d0862b7033dbaa"
  },
  {
    "timestamp": 1767338071453,
    "user": "poemstars🌼🌟",
    "userId": "spotify:user:21jq6cmbitks7givwb7zvsyxy",
    "track": "Beauty And A Beat",
    "artist": "Justin Bieber, Nicki Minaj",
    "uri": "spotify:track:6QFCMUUq1T2Vf5sFUXcuQ7",
    "imageUrl": "https://i.scdn.co/image/ab67616d0000b273f1d02a6cec967f8b6b78f76e"
  },
  {
    "timestamp": 1767337861650,
    "user": "poemstars🌼🌟",
    "userId": "spotify:user:21jq6cmbitks7givwb7zvsyxy",
    "track": "One Less Lonely Girl",
    "artist": "Justin Bieber",
    "uri": "spotify:track:69ghzc538EQSVon2Gm3wrr",
    "imageUrl": "https://i.scdn.co/image/ab67616d0000b2737c3bb9f74a98f60bdda6c9a7"
  },
  {
    "timestamp": 1767337531292,
    "user": "poemstars🌼🌟",
    "userId": "spotify:user:21jq6cmbitks7givwb7zvsyxy",
    "track": "Favorite Girl",
    "artist": "Justin Bieber",
    "uri": "spotify:track:4nTjkWK590oBDcnIxTr1mI",
    "imageUrl": "https://i.scdn.co/image/ab67616d0000b2737c3bb9f74a98f60bdda6c9a7"
  },
  {
    "timestamp": 1767337291436,
    "user": "poemstars🌼🌟",
    "userId": "spotify:user:21jq6cmbitks7givwb7zvsyxy",
    "track": "Somebody To Love",
    "artist": "Justin Bieber",
    "uri": "spotify:track:3rLIv187BhjyweFe89SgLn",
    "imageUrl": "https://i.scdn.co/image/ab67616d0000b273629dc9e2e3bc20bbd7d92e4a"
  },
  {
    "timestamp": 1767336961543,
    "user": "poemstars🌼🌟",
    "userId": "spotify:user:21jq6cmbitks7givwb7zvsyxy",
    "track": "Never Say Never",
    "artist": "Justin Bieber, Jaden",
    "uri": "spotify:track:5GYbkDveRD2I8M5ZJ14hWn",
    "imageUrl": "https://i.scdn.co/image/ab67616d0000b27349130b16d4190db1d6822e59"
  },
  {
    "timestamp": 1767336601496,
    "user": "poemstars🌼🌟",
    "userId": "spotify:user:21jq6cmbitks7givwb7zvsyxy",
    "track": "Cinta Sempurna",
    "artist": "Raisa",
    "uri": "spotify:track:2LC4JvZwREANa6tqlcA1er",
    "imageUrl": "https://i.scdn.co/image/ab67616d0000b2738bd2fdd47fa594b1362682a9"
  },
  {
    "timestamp": 1767336241315,
    "user": "poemstars🌼🌟",
    "userId": "spotify:user:21jq6cmbitks7givwb7zvsyxy",
    "track": "Serba Salah",
    "artist": "Raisa",
    "uri": "spotify:track:3jMXORZIqN8biiXVJXP3vk",
    "imageUrl": "https://i.scdn.co/image/ab67616d0000b2738bd2fdd47fa594b1362682a9"
  },
  {
    "timestamp": 1767335462166,
    "user": "poemstars🌼🌟",
    "userId": "spotify:user:21jq6cmbitks7givwb7zvsyxy",
    "track": "Could It Be",
    "artist": "Raisa",
    "uri": "spotify:track:6Khn20yWc0YGJy1wbkz3Be",
    "imageUrl": "https://i.scdn.co/image/ab67616d0000b2738bd2fdd47fa594b1362682a9"
  }
]