{
  "friends": [
    {
      "timestamp": 1764863856499,
      "user": {
        "uri": "spotify:user:21jq6cmbitks7givwb7zvsyxy",
        "name": "poemstars🌼🌟",
        "imageUrl": "https://i.scdn.co/image/ab6775700000ee852484b5c72c0e677065c476dd"
      },
      "track": {
        "uri": "spotify:track:3iVcZ5G6tvkXZkZKlMpIUs",
        "name": "Alright",
        "imageUrl": "https://i.scdn.co/image/ab67616d0000b273cdb645498cd3d8a2db4d05e1",
        "album": {
          "uri": "spotify:album:7ycBtnsMtyVbbwTfJwRjSP",
          "name": "To Pimp A Butterfly"
        },
        "artist": {
          "uri": "spotify:artist:2YZyLoL8N0Wb9xBt1NhZWg",
          "name": "Kendrick Lamar"
        },
        "context": {
          "uri": "spotify:artist:2YZyLoL8N0Wb9xBt1NhZWg",
          "name": "artist",
          "index": 0
        }
      }
    }
  ]
}