{
  "friends": [
    {
      "timestamp": 1759236146484,
      "user": {
        "uri": "spotify:user:dandyraka_",
        "name": "Dandy 🫵🏻😁",
        "imageUrl": "https://scontent-tpe1-1.xx.fbcdn.net/v/t39.30808-1/368014355_3039288076206294_6645918189275641807_n.jpg?stp=dst-jpg_s320x320_tt6&_nc_cat=111&ccb=1-7&_nc_sid=79bf43&_nc_ohc=dlBVIj7PBsEQ7kNvwEpGBs2&_nc_oc=AdkCkUEnm5tEVSUi61nZjyHYHzspCJFxAUuuC6BUdlG89lygJM84y-QK2R1AJ0es1YAZOADugrRqtW3HD1yDH8vL&_nc_zt=24&_nc_ht=scontent-tpe1-1.xx&edm=AP4hL3IEAAAA&_nc_gid=x_hs8QdxrfgsqJZ-k7y7qA&oh=00_AfZmoS0m-QtmEOrzHaoluGzUc_ZizPfciwiOUJwxWRRCPw&oe=68E13128"
      },
      "track": {
        "uri": "spotify:track:7mKP7fGySWEJv2jVX1H7Ps",
        "name": "Online",
        "imageUrl": "https://i.scdn.co/image/ab67616d0000b27305460009185b46b36b03db61",
        "album": {
          "uri": "spotify:album:6eCbsmU4PhyOalhGzac4M7",
          "name": "Online"
        },
        "artist": {
          "uri": "spotify:artist:6N981Y5JhkKTEH37pq4ImZ",
          "name": "Saykoji"
        },
        "context": {
          "uri": "spotify:playlist:080uvEAtAx6i7AjHvSDeER",
          "name": "playlist",
          "index": 0
        }
      }
    },
    {
      "timestamp": 1759236147183,
      "user": {
        "uri": "spotify:user:21jq6cmbitks7givwb7zvsyxy",
        "name": "poemstars🌼🌟",
        "imageUrl": "https://i.scdn.co/image/ab6775700000ee852484b5c72c0e677065c476dd"
      },
      "track": {
        "uri": "spotify:track:6RAxgUG90f39dVSGUr4qOd",
        "name": "Kisah Tanpa Dirimu",
        "imageUrl": "https://i.scdn.co/image/ab67616d0000b273d7105ffabf2ff9ddd265eab1",
        "album": {
          "uri": "spotify:album:6WyxwTMDu7MdmWKZ2m4lCe",
          "name": "Devaki"
        },
        "artist": {
          "uri": "spotify:artist:7lXTU6VtJQWfiN2vuZyzqf",
          "name": "Anggis Devaki"
        },
        "context": {
          "uri": null,
          "name": null,
          "index": 0
        }
      }
    }
  ]
}